Metadata-Version: 2.4
Name: adafruit-circuitpython-rfm9x
Version: 2.2.19
Summary: CircuitPython library for RFM95/6/7/8 LoRa 433/915mhz radio modules.
Author-email: Adafruit Industries <circuitpython@adafruit.com>
License: MIT
Project-URL: Homepage, https://github.com/adafruit/Adafruit_CircuitPython_RFM9x
Keywords: adafruit,lora,radio,rfm95,rfm9x,rfm96,rfm97,rfm98,hardware,micropython,circuitpython
Classifier: Intended Audience :: Developers
Classifier: Topic :: Software Development :: Libraries
Classifier: Topic :: Software Development :: Embedded Systems
Classifier: Topic :: System :: Hardware
Classifier: License :: OSI Approved :: MIT License
Classifier: Programming Language :: Python :: 3
License-File: LICENSE
Requires-Dist: Adafruit-Blinka>=7.2.3
Requires-Dist: adafruit-circuitpython-busdevice
Dynamic: license-file
